mpteval/__init__.py
mpteval/articulation.py
mpteval/benchmarks.py
mpteval/dynamics.py
mpteval/harmony.py
mpteval/timing.py
mpteval/utils.py
mpteval/assets/pred.mid
mpteval/assets/ref.mid
mpteval-0.1.4.dist-info/licenses/LICENSE
mpteval-0.1.4.dist-info/METADATA
mpteval-0.1.4.dist-info/WHEEL
mpteval-0.1.4.dist-info/top_level.txt
mpteval-0.1.4.dist-info/RECORD
