Metadata-Version: 2.4
Name: mpteval
Version: 0.1.4
Summary: Musically informed piano transcription metrics
Author: Lukáš Samuel Marták, Carlos Cancino-Chacón
Author-email: Patricia Hu <patricia.hu@jku.at>
Project-URL: Homepage, https://github.com/CPJKU/mpteval
Project-URL: Issues, https://github.com/CPJKU/mpteval/issues
Classifier: Programming Language :: Python :: 3
Classifier: License :: OSI Approved :: MIT License
Classifier: Operating System :: OS Independent
Requires-Python: >=3.9
License-File: LICENSE
Requires-Dist: numpy==1.26.4
Requires-Dist: scipy==1.12.0
Requires-Dist: partitura==1.7.0
Requires-Dist: matplotlib==3.7.0
Requires-Dist: fastdtw==0.3.4
Dynamic: license-file
